algo_method_tools/__init__.py
algo_method_tools/main.py
algo_method_tools-0.1.2.dist-info/entry_points.txt
algo_method_tools-0.1.2.dist-info/LICENSE
algo_method_tools-0.1.2.dist-info/WHEEL
algo_method_tools-0.1.2.dist-info/METADATA
algo_method_tools-0.1.2.dist-info/RECORD
